ephor_cli/__init__.py
ephor_cli/constant.py
ephor_cli/agent_server/__init__.py
ephor_cli/agent_server/agent.py
ephor_cli/agent_server/server.py
ephor_cli/agent_server/task_manager.py
ephor_cli/agent_server/sample-agent-configs/gdoc-agent.yml
ephor_cli/agent_server/sample-agent-configs/giphy-agent.yml
ephor_cli/clients/ddb/agent.py
ephor_cli/clients/ddb/base.py
ephor_cli/clients/ddb/conversation.py
ephor_cli/clients/ddb/conversation_attachment.py
ephor_cli/clients/ddb/event.py
ephor_cli/clients/ddb/message.py
ephor_cli/clients/ddb/task.py
ephor_cli/conversation_server/__init__.py
ephor_cli/conversation_server/conference_call_manager.py
ephor_cli/conversation_server/host_agent.py
ephor_cli/conversation_server/host_manager.py
ephor_cli/conversation_server/server.py
ephor_cli/mcp_adapters/__init__.py
ephor_cli/mcp_adapters/client.py
ephor_cli/mcp_adapters/sessions.py
ephor_cli/mcp_adapters/tools.py
ephor_cli/scripts/delete_conversations.py
ephor_cli/scripts/test_agent_server.py
ephor_cli/scripts/test_conversation_sse.py
ephor_cli/services/__init__.py
ephor_cli/services/agent.py
ephor_cli/services/cache_service.py
ephor_cli/services/conversation.py
ephor_cli/services/conversation_attachment.py
ephor_cli/services/conversation_indexing_service.py
ephor_cli/services/embedding_service.py
ephor_cli/services/event.py
ephor_cli/services/image_captioning_service.py
ephor_cli/services/message.py
ephor_cli/services/opensearch_client.py
ephor_cli/services/s3.py
ephor_cli/services/task.py
ephor_cli/services/text_processor.py
ephor_cli/types/__init__.py
ephor_cli/types/agent.py
ephor_cli/types/context_search.py
ephor_cli/types/conversation.py
ephor_cli/types/conversation_attachment.py
ephor_cli/types/event.py
ephor_cli/types/llm.py
ephor_cli/types/message.py
ephor_cli/types/sse.py
ephor_cli/types/task.py
ephor_cli/utils/__init__.py
ephor_cli/utils/agent_card.py
ephor_cli/utils/attachments.py
ephor_cli/utils/chunk_streamer.py
ephor_cli/utils/message.py
ephor_cli-0.7.28.dist-info/METADATA
ephor_cli-0.7.28.dist-info/WHEEL
ephor_cli-0.7.28.dist-info/entry_points.txt
ephor_cli-0.7.28.dist-info/RECORD
