Metadata-Version: 2.4
Name: ephor-cli
Version: 0.7.28
Summary: Add your description here
Author-email: amandal-cn <mandal.ashish@codenation.co.in>
Requires-Python: >=3.13
Requires-Dist: boto3==1.38.8
Requires-Dist: click==8.1.8
Requires-Dist: colorama==0.4.6
Requires-Dist: google-a2a
Requires-Dist: google-adk==0.3.0
Requires-Dist: langchain-anthropic>=0.3.13
Requires-Dist: langchain-aws>=0.2.23
Requires-Dist: langchain-google-genai>=2.1.4
Requires-Dist: langchain-openai>=0.3.18
Requires-Dist: langchain>=0.3.25
Requires-Dist: langgraph==0.4.10
Requires-Dist: mcp>=1.9.3
Requires-Dist: openai>=1.85.0
Requires-Dist: openpyxl>=3.1.0
Requires-Dist: opensearch-py>=2.8.0
Requires-Dist: pypdf2>=3.0.1
Requires-Dist: python-docx>=1.1.0
Requires-Dist: python-dotenv==1.1.0
Requires-Dist: requests-aws4auth>=1.3.1
Requires-Dist: tiktoken>=0.9.0
